pyemoji/__init__.py
pyemoji/compat.py
pyemoji/main.py
pyemoji-1.0.4.dist-info/DESCRIPTION.rst
pyemoji-1.0.4.dist-info/METADATA
pyemoji-1.0.4.dist-info/RECORD
pyemoji-1.0.4.dist-info/WHEEL
pyemoji-1.0.4.dist-info/metadata.json
pyemoji-1.0.4.dist-info/top_level.txt
