Metadata-Version: 2.0
Name: pyemoji
Version: 1.0.4
Summary: Emoji Convert & Replace & Entities & Joiner
Home-page: https://github.com/Brightcells/pyemoji
Author: Hackathon
Author-email: kimi.huang@brightcells.com
License: UNKNOWN
Platform: UNKNOWN
Classifier: License :: OSI Approved :: BSD License
Classifier: Programming Language :: Python
Classifier: Programming Language :: Python :: 2
Classifier: Programming Language :: Python :: 2.6
Classifier: Programming Language :: Python :: 2.7
Classifier: Programming Language :: Python :: 3
Classifier: Programming Language :: Python :: 3.2
Classifier: Programming Language :: Python :: 3.3
Classifier: Programming Language :: Python :: 3.4
Classifier: Topic :: Software Development :: Libraries :: Python Modules
